guake/__init__.py
guake/_version.py
guake/about.py
guake/boxes.py
guake/callbacks.py
guake/common.py
guake/customcommands.py
guake/dbusiface.py
guake/dialogs.py
guake/globals.py
guake/gsettings.py
guake/guake_app.py
guake/guake_logging.py
guake/guake_toggle.py
guake/keybindings.py
guake/main.py
guake/menus.py
guake/notebook.py
guake/notifier.py
guake/palettes.py
guake/paths.py
guake/prefs.py
guake/settings.py
guake/simplegladeapp.py
guake/split_utils.py
guake/support.py
guake/terminal.py
guake/theme.py
guake/utils.py
guake/data/__init__.py
guake/data/about.glade
guake/data/autostart-guake.desktop
guake/data/guake-prefs.template.desktop
guake/data/guake.desktop.metainfo.xml
guake/data/guake.glade
guake/data/guake.template.desktop
guake/data/org.guake.gschema.xml
guake/data/prefs.glade
guake/data/search.glade
guake/data/pixmaps/add_tab.png
guake/data/pixmaps/guake-128.png
guake/data/pixmaps/guake-48.png
guake/data/pixmaps/guake-64.png
guake/data/pixmaps/guake-notification.png
guake/data/pixmaps/guake-tray.png
guake/data/pixmaps/guake-tray.svg
guake/data/pixmaps/guake.png
guake/data/pixmaps/intro-large.jpg
guake/data/pixmaps/intro-medium.jpg
guake/data/pixmaps/intro-small.jpg
guake/data/pixmaps/quick-open-python-exception.png
guake/data/pixmaps/quick-open-selection.png
guake/data/pixmaps/quick-open.png
guake/data/pixmaps/screenshot-fullscreen.jpg
guake/data/pixmaps/screenshot-small.jpg
guake-3.10.dist-info/COPYING
guake-3.10.dist-info/METADATA
guake-3.10.dist-info/WHEEL
guake-3.10.dist-info/entry_points.txt
guake-3.10.dist-info/top_level.txt
guake-3.10.dist-info/RECORD
