Metadata-Version: 2.1
Name: guake
Version: 3.10
Summary: Guake Terminal
Home-page: https://github.com/Guake/guake
Author: Gaetan Semet
Author-email: gaetan@xeberon.net
License: UNKNOWN
Platform: UNKNOWN
Classifier: Intended Audience :: Information Technology
Classifier: Intended Audience :: System Administrators
Classifier: License :: OSI Approved :: GNU General Public License v2 or later (GPLv2+)
Classifier: Operating System :: POSIX :: Linux
Classifier: Programming Language :: Python :: 3.8
Classifier: Programming Language :: Python :: 3.9
Classifier: Programming Language :: Python :: 3.10
Classifier: Programming Language :: Python :: 3.11
Classifier: Topic :: Terminals
Classifier: Topic :: Terminals :: Terminal Emulators/X Terminals
Classifier: Topic :: Desktop Environment :: Gnome
License-File: COPYING
Requires-Dist: typing ; python_version < "3.5"
Requires-Dist: importlib-metadata ; python_version < "3.8"
